<?xml version="1.0" encoding="UTF-8"?>
<BaliMessageLog>
    <Task name="MapVerilogSimFile">
        <Message>
            <ID>35400250</ID>
            <Severity>Info</Severity>
            <Dynamic>0</Dynamic>
        </Message>
    </Task>
    <Task name="MapVHDLSimFile">
        <Message>
            <ID>35400250</ID>
            <Severity>Info</Severity>
            <Dynamic>0</Dynamic>
        </Message>
    </Task>
    <Task name="Map">
        <Message>
            <ID>1166064</ID>
            <Severity>Warning</Severity>
            <Dynamic>input</Dynamic>
            <Dynamic>clk_aux</Dynamic>
        </Message>
        <Message>
            <ID>51001046</ID>
            <Severity>Warning</Severity>
            <Dynamic>clk_aux</Dynamic>
        </Message>
    </Task>
    <Task name="Lattice_Synthesis">
        <Message>
            <ID>35002000</ID>
            <Severity>Info</Severity>
        </Message>
        <Message>
            <ID>35001781</ID>
            <Severity>Info</Severity>
        </Message>
        <Message>
            <ID>35921504</ID>
            <Severity>Info</Severity>
            <Dynamic></Dynamic>
            <Dynamic>C:/devel/yard-ice/fpga/lattice/rev2</Dynamic>
        </Message>
        <Message>
            <ID>35921012</ID>
            <Severity>Info</Severity>
            <Dynamic>c:/devel/yard-ice/src/fpga/counter.vhdl(30): </Dynamic>
            <Dynamic>counter</Dynamic>
            <Navigation>c:/devel/yard-ice/src/fpga/counter.vhdl</Navigation>
            <Navigation>30</Navigation>
        </Message>
        <Message>
            <ID>35921010</ID>
            <Severity>Info</Severity>
            <Dynamic>c:/devel/yard-ice/src/fpga/counter.vhdl(59): </Dynamic>
            <Dynamic>rtl</Dynamic>
            <Navigation>c:/devel/yard-ice/src/fpga/counter.vhdl</Navigation>
            <Navigation>59</Navigation>
        </Message>
        <Message>
            <ID>35921012</ID>
            <Severity>Info</Severity>
            <Dynamic>c:/devel/yard-ice/src/fpga/syncfifo.vhdl(31): </Dynamic>
            <Dynamic>syncfifo</Dynamic>
            <Navigation>c:/devel/yard-ice/src/fpga/syncfifo.vhdl</Navigation>
            <Navigation>31</Navigation>
        </Message>
        <Message>
            <ID>35921010</ID>
            <Severity>Info</Severity>
            <Dynamic>c:/devel/yard-ice/src/fpga/syncfifo.vhdl(53): </Dynamic>
            <Dynamic>rtl</Dynamic>
            <Navigation>c:/devel/yard-ice/src/fpga/syncfifo.vhdl</Navigation>
            <Navigation>53</Navigation>
        </Message>
        <Message>
            <ID>35921012</ID>
            <Severity>Info</Severity>
            <Dynamic>c:/devel/yard-ice/src/fpga/cram_adaptor.vhdl(35): </Dynamic>
            <Dynamic>cram_adaptor</Dynamic>
            <Navigation>c:/devel/yard-ice/src/fpga/cram_adaptor.vhdl</Navigation>
            <Navigation>35</Navigation>
        </Message>
        <Message>
            <ID>35921010</ID>
            <Severity>Info</Severity>
            <Dynamic>c:/devel/yard-ice/src/fpga/cram_adaptor.vhdl(74): </Dynamic>
            <Dynamic>rtl</Dynamic>
            <Navigation>c:/devel/yard-ice/src/fpga/cram_adaptor.vhdl</Navigation>
            <Navigation>74</Navigation>
        </Message>
        <Message>
            <ID>35921012</ID>
            <Severity>Info</Severity>
            <Dynamic>c:/devel/yard-ice/src/fpga/dpram.vhdl(30): </Dynamic>
            <Dynamic>dpram</Dynamic>
            <Navigation>c:/devel/yard-ice/src/fpga/dpram.vhdl</Navigation>
            <Navigation>30</Navigation>
        </Message>
        <Message>
            <ID>35921010</ID>
            <Severity>Info</Severity>
            <Dynamic>c:/devel/yard-ice/src/fpga/dpram.vhdl(50): </Dynamic>
            <Dynamic>rtl</Dynamic>
            <Navigation>c:/devel/yard-ice/src/fpga/dpram.vhdl</Navigation>
            <Navigation>50</Navigation>
        </Message>
        <Message>
            <ID>35921012</ID>
            <Severity>Info</Severity>
            <Dynamic>c:/devel/yard-ice/src/fpga/jtag_clk_scaler.vhdl(31): </Dynamic>
            <Dynamic>jtag_clk_scaler</Dynamic>
            <Navigation>c:/devel/yard-ice/src/fpga/jtag_clk_scaler.vhdl</Navigation>
            <Navigation>31</Navigation>
        </Message>
        <Message>
            <ID>35921010</ID>
            <Severity>Info</Severity>
            <Dynamic>c:/devel/yard-ice/src/fpga/jtag_clk_scaler.vhdl(51): </Dynamic>
            <Dynamic>rtl</Dynamic>
            <Navigation>c:/devel/yard-ice/src/fpga/jtag_clk_scaler.vhdl</Navigation>
            <Navigation>51</Navigation>
        </Message>
        <Message>
            <ID>35921012</ID>
            <Severity>Info</Severity>
            <Dynamic>c:/devel/yard-ice/src/fpga/jtag_counter.vhdl(30): </Dynamic>
            <Dynamic>jtag_counter</Dynamic>
            <Navigation>c:/devel/yard-ice/src/fpga/jtag_counter.vhdl</Navigation>
            <Navigation>30</Navigation>
        </Message>
        <Message>
            <ID>35921010</ID>
            <Severity>Info</Severity>
            <Dynamic>c:/devel/yard-ice/src/fpga/jtag_counter.vhdl(59): </Dynamic>
            <Dynamic>rtl</Dynamic>
            <Navigation>c:/devel/yard-ice/src/fpga/jtag_counter.vhdl</Navigation>
            <Navigation>59</Navigation>
        </Message>
        <Message>
            <ID>35921012</ID>
            <Severity>Info</Severity>
            <Dynamic>c:/devel/yard-ice/src/fpga/jtag_cmem.vhdl(33): </Dynamic>
            <Dynamic>jtag_cram16</Dynamic>
            <Navigation>c:/devel/yard-ice/src/fpga/jtag_cmem.vhdl</Navigation>
            <Navigation>33</Navigation>
        </Message>
        <Message>
            <ID>35921010</ID>
            <Severity>Info</Severity>
            <Dynamic>c:/devel/yard-ice/src/fpga/jtag_cmem.vhdl(57): </Dynamic>
            <Dynamic>rtl</Dynamic>
            <Navigation>c:/devel/yard-ice/src/fpga/jtag_cmem.vhdl</Navigation>
            <Navigation>57</Navigation>
        </Message>
        <Message>
            <ID>35921012</ID>
            <Severity>Info</Severity>
            <Dynamic>c:/devel/yard-ice/src/fpga/jtag_desc_ram.vhdl(6): </Dynamic>
            <Dynamic>jtag_desc_ram</Dynamic>
            <Navigation>c:/devel/yard-ice/src/fpga/jtag_desc_ram.vhdl</Navigation>
            <Navigation>6</Navigation>
        </Message>
        <Message>
            <ID>35921010</ID>
            <Severity>Info</Severity>
            <Dynamic>c:/devel/yard-ice/src/fpga/jtag_desc_ram.vhdl(27): </Dynamic>
            <Dynamic>rtl</Dynamic>
            <Navigation>c:/devel/yard-ice/src/fpga/jtag_desc_ram.vhdl</Navigation>
            <Navigation>27</Navigation>
        </Message>
        <Message>
            <ID>35921012</ID>
            <Severity>Info</Severity>
            <Dynamic>c:/devel/yard-ice/src/fpga/jtag_enh_ckgen.vhdl(30): </Dynamic>
            <Dynamic>jtag_enh_ckgen</Dynamic>
            <Navigation>c:/devel/yard-ice/src/fpga/jtag_enh_ckgen.vhdl</Navigation>
            <Navigation>30</Navigation>
        </Message>
        <Message>
            <ID>35921010</ID>
            <Severity>Info</Severity>
            <Dynamic>c:/devel/yard-ice/src/fpga/jtag_enh_ckgen.vhdl(61): </Dynamic>
            <Dynamic>rtl</Dynamic>
            <Navigation>c:/devel/yard-ice/src/fpga/jtag_enh_ckgen.vhdl</Navigation>
            <Navigation>61</Navigation>
        </Message>
        <Message>
            <ID>35921012</ID>
            <Severity>Info</Severity>
            <Dynamic>c:/devel/yard-ice/src/fpga/jtag_enh_ecu.vhdl(69): </Dynamic>
            <Dynamic>jtag_enh_ecu</Dynamic>
            <Navigation>c:/devel/yard-ice/src/fpga/jtag_enh_ecu.vhdl</Navigation>
            <Navigation>69</Navigation>
        </Message>
        <Message>
            <ID>35921010</ID>
            <Severity>Info</Severity>
            <Dynamic>c:/devel/yard-ice/src/fpga/jtag_enh_ecu.vhdl(125): </Dynamic>
            <Dynamic>rtl</Dynamic>
            <Navigation>c:/devel/yard-ice/src/fpga/jtag_enh_ecu.vhdl</Navigation>
            <Navigation>125</Navigation>
        </Message>
        <Message>
            <ID>35921012</ID>
            <Severity>Info</Severity>
            <Dynamic>c:/devel/yard-ice/src/fpga/jtag_enh_io.vhdl(30): </Dynamic>
            <Dynamic>jtag_enh_io</Dynamic>
            <Navigation>c:/devel/yard-ice/src/fpga/jtag_enh_io.vhdl</Navigation>
            <Navigation>30</Navigation>
        </Message>
        <Message>
            <ID>35921010</ID>
            <Severity>Info</Severity>
            <Dynamic>c:/devel/yard-ice/src/fpga/jtag_enh_io.vhdl(59): </Dynamic>
            <Dynamic>rtl</Dynamic>
            <Navigation>c:/devel/yard-ice/src/fpga/jtag_enh_io.vhdl</Navigation>
            <Navigation>59</Navigation>
        </Message>
        <Message>
            <ID>35921012</ID>
            <Severity>Info</Severity>
            <Dynamic>c:/devel/yard-ice/src/fpga/jtag_enh_rx.vhdl(31): </Dynamic>
            <Dynamic>jtag_enh_rx</Dynamic>
            <Navigation>c:/devel/yard-ice/src/fpga/jtag_enh_rx.vhdl</Navigation>
            <Navigation>31</Navigation>
        </Message>
        <Message>
            <ID>35921010</ID>
            <Severity>Info</Severity>
            <Dynamic>c:/devel/yard-ice/src/fpga/jtag_enh_rx.vhdl(86): </Dynamic>
            <Dynamic>rtl</Dynamic>
            <Navigation>c:/devel/yard-ice/src/fpga/jtag_enh_rx.vhdl</Navigation>
            <Navigation>86</Navigation>
        </Message>
        <Message>
            <ID>35921012</ID>
            <Severity>Info</Severity>
            <Dynamic>c:/devel/yard-ice/src/fpga/jtag_enh_shift_ctrl.vhdl(31): </Dynamic>
            <Dynamic>jtag_enh_shift_ctrl</Dynamic>
            <Navigation>c:/devel/yard-ice/src/fpga/jtag_enh_shift_ctrl.vhdl</Navigation>
            <Navigation>31</Navigation>
        </Message>
        <Message>
            <ID>35921010</ID>
            <Severity>Info</Severity>
            <Dynamic>c:/devel/yard-ice/src/fpga/jtag_enh_shift_ctrl.vhdl(72): </Dynamic>
            <Dynamic>rtl</Dynamic>
            <Navigation>c:/devel/yard-ice/src/fpga/jtag_enh_shift_ctrl.vhdl</Navigation>
            <Navigation>72</Navigation>
        </Message>
        <Message>
            <ID>35921012</ID>
            <Severity>Info</Severity>
            <Dynamic>c:/devel/yard-ice/src/fpga/jtag_enh_tx.vhdl(31): </Dynamic>
            <Dynamic>jtag_enh_tx</Dynamic>
            <Navigation>c:/devel/yard-ice/src/fpga/jtag_enh_tx.vhdl</Navigation>
            <Navigation>31</Navigation>
        </Message>
        <Message>
            <ID>35921010</ID>
            <Severity>Info</Severity>
            <Dynamic>c:/devel/yard-ice/src/fpga/jtag_enh_tx.vhdl(70): </Dynamic>
            <Dynamic>rtl</Dynamic>
            <Navigation>c:/devel/yard-ice/src/fpga/jtag_enh_tx.vhdl</Navigation>
            <Navigation>70</Navigation>
        </Message>
        <Message>
            <ID>35921012</ID>
            <Severity>Info</Severity>
            <Dynamic>c:/devel/yard-ice/src/fpga/jtag_enh_shifter.vhdl(35): </Dynamic>
            <Dynamic>jtag_enh_shifter</Dynamic>
            <Navigation>c:/devel/yard-ice/src/fpga/jtag_enh_shifter.vhdl</Navigation>
            <Navigation>35</Navigation>
        </Message>
        <Message>
            <ID>35921010</ID>
            <Severity>Info</Severity>
            <Dynamic>c:/devel/yard-ice/src/fpga/jtag_enh_shifter.vhdl(130): </Dynamic>
            <Dynamic>structure</Dynamic>
            <Navigation>c:/devel/yard-ice/src/fpga/jtag_enh_shifter.vhdl</Navigation>
            <Navigation>130</Navigation>
        </Message>
        <Message>
            <ID>35921012</ID>
            <Severity>Info</Severity>
            <Dynamic>c:/devel/yard-ice/src/fpga/jtag_io_dpram.vhdl(30): </Dynamic>
            <Dynamic>jtag_io_dpram</Dynamic>
            <Navigation>c:/devel/yard-ice/src/fpga/jtag_io_dpram.vhdl</Navigation>
            <Navigation>30</Navigation>
        </Message>
        <Message>
            <ID>35921010</ID>
            <Severity>Info</Severity>
            <Dynamic>c:/devel/yard-ice/src/fpga/jtag_io_dpram.vhdl(50): </Dynamic>
            <Dynamic>rtl</Dynamic>
            <Navigation>c:/devel/yard-ice/src/fpga/jtag_io_dpram.vhdl</Navigation>
            <Navigation>50</Navigation>
        </Message>
        <Message>
            <ID>35921012</ID>
            <Severity>Info</Severity>
            <Dynamic>c:/devel/yard-ice/src/fpga/jtag_led_drv.vhdl(31): </Dynamic>
            <Dynamic>jtag_led_drv</Dynamic>
            <Navigation>c:/devel/yard-ice/src/fpga/jtag_led_drv.vhdl</Navigation>
            <Navigation>31</Navigation>
        </Message>
        <Message>
            <ID>35921010</ID>
            <Severity>Info</Severity>
            <Dynamic>c:/devel/yard-ice/src/fpga/jtag_led_drv.vhdl(56): </Dynamic>
            <Dynamic>rtl</Dynamic>
            <Navigation>c:/devel/yard-ice/src/fpga/jtag_led_drv.vhdl</Navigation>
            <Navigation>56</Navigation>
        </Message>
        <Message>
            <ID>35921012</ID>
            <Severity>Info</Severity>
            <Dynamic>c:/devel/yard-ice/src/fpga/jtag_reg.vhdl(30): </Dynamic>
            <Dynamic>jtag_reg</Dynamic>
            <Navigation>c:/devel/yard-ice/src/fpga/jtag_reg.vhdl</Navigation>
            <Navigation>30</Navigation>
        </Message>
        <Message>
            <ID>35921010</ID>
            <Severity>Info</Severity>
            <Dynamic>c:/devel/yard-ice/src/fpga/jtag_reg.vhdl(59): </Dynamic>
            <Dynamic>rtl</Dynamic>
            <Navigation>c:/devel/yard-ice/src/fpga/jtag_reg.vhdl</Navigation>
            <Navigation>59</Navigation>
        </Message>
        <Message>
            <ID>35921012</ID>
            <Severity>Info</Severity>
            <Dynamic>c:/devel/yard-ice/src/fpga/sram.vhdl(30): </Dynamic>
            <Dynamic>sram</Dynamic>
            <Navigation>c:/devel/yard-ice/src/fpga/sram.vhdl</Navigation>
            <Navigation>30</Navigation>
        </Message>
        <Message>
            <ID>35921010</ID>
            <Severity>Info</Severity>
            <Dynamic>c:/devel/yard-ice/src/fpga/sram.vhdl(46): </Dynamic>
            <Dynamic>rtl</Dynamic>
            <Navigation>c:/devel/yard-ice/src/fpga/sram.vhdl</Navigation>
            <Navigation>46</Navigation>
        </Message>
        <Message>
            <ID>35921012</ID>
            <Severity>Info</Severity>
            <Dynamic>c:/devel/yard-ice/fpga/lattice/ddr_phy.vhd(14): </Dynamic>
            <Dynamic>ddr_phy</Dynamic>
            <Navigation>c:/devel/yard-ice/fpga/lattice/ddr_phy.vhd</Navigation>
            <Navigation>14</Navigation>
        </Message>
        <Message>
            <ID>35921010</ID>
            <Severity>Info</Severity>
            <Dynamic>c:/devel/yard-ice/fpga/lattice/ddr_phy.vhd(62): </Dynamic>
            <Dynamic>structure</Dynamic>
            <Navigation>c:/devel/yard-ice/fpga/lattice/ddr_phy.vhd</Navigation>
            <Navigation>62</Navigation>
        </Message>
        <Message>
            <ID>35921012</ID>
            <Severity>Info</Severity>
            <Dynamic>c:/devel/yard-ice/fpga/lattice/ddr_phy.vhd(14): </Dynamic>
            <Dynamic>ddr_phy</Dynamic>
            <Navigation>c:/devel/yard-ice/fpga/lattice/ddr_phy.vhd</Navigation>
            <Navigation>14</Navigation>
        </Message>
        <Message>
            <ID>35921010</ID>
            <Severity>Info</Severity>
            <Dynamic>c:/devel/yard-ice/fpga/lattice/ddr_phy.vhd(62): </Dynamic>
            <Dynamic>structure</Dynamic>
            <Navigation>c:/devel/yard-ice/fpga/lattice/ddr_phy.vhd</Navigation>
            <Navigation>62</Navigation>
        </Message>
        <Message>
            <ID>35921012</ID>
            <Severity>Info</Severity>
            <Dynamic>c:/devel/yard-ice/fpga/lattice/vhdl/ddr_sdram_dual.vhdl(67): </Dynamic>
            <Dynamic>ddr_sdram_dual</Dynamic>
            <Navigation>c:/devel/yard-ice/fpga/lattice/vhdl/ddr_sdram_dual.vhdl</Navigation>
            <Navigation>67</Navigation>
        </Message>
        <Message>
            <ID>35921010</ID>
            <Severity>Info</Severity>
            <Dynamic>c:/devel/yard-ice/fpga/lattice/vhdl/ddr_sdram_dual.vhdl(131): </Dynamic>
            <Dynamic>rtl</Dynamic>
            <Navigation>c:/devel/yard-ice/fpga/lattice/vhdl/ddr_sdram_dual.vhdl</Navigation>
            <Navigation>131</Navigation>
        </Message>
        <Message>
            <ID>35921012</ID>
            <Severity>Info</Severity>
            <Dynamic>c:/devel/yard-ice/src/fpga/yard_ice.vhdl(66): </Dynamic>
            <Dynamic>yard_ice</Dynamic>
            <Navigation>c:/devel/yard-ice/src/fpga/yard_ice.vhdl</Navigation>
            <Navigation>66</Navigation>
        </Message>
        <Message>
            <ID>35921010</ID>
            <Severity>Info</Severity>
            <Dynamic>c:/devel/yard-ice/src/fpga/yard_ice.vhdl(123): </Dynamic>
            <Dynamic>structure</Dynamic>
            <Navigation>c:/devel/yard-ice/src/fpga/yard_ice.vhdl</Navigation>
            <Navigation>123</Navigation>
        </Message>
        <Message>
            <ID>35928037</ID>
            <Severity>Warning</Severity>
            <Dynamic>c:/devel/yard-ice/src/fpga/syncfifo.vhdl(78): </Dynamic>
            <Navigation>c:/devel/yard-ice/src/fpga/syncfifo.vhdl</Navigation>
            <Navigation>78</Navigation>
        </Message>
        <Message>
            <ID>35928037</ID>
            <Severity>Warning</Severity>
            <Dynamic>c:/devel/yard-ice/src/fpga/syncfifo.vhdl(84): </Dynamic>
            <Navigation>c:/devel/yard-ice/src/fpga/syncfifo.vhdl</Navigation>
            <Navigation>84</Navigation>
        </Message>
        <Message>
            <ID>35921303</ID>
            <Severity>Warning</Severity>
            <Dynamic>c:/devel/yard-ice/src/fpga/yard_ice.vhdl(362): </Dynamic>
            <Dynamic>'U'</Dynamic>
            <Dynamic>s_ddr_cmd_stb</Dynamic>
            <Navigation>c:/devel/yard-ice/src/fpga/yard_ice.vhdl</Navigation>
            <Navigation>362</Navigation>
        </Message>
        <Message>
            <ID>35921303</ID>
            <Severity>Warning</Severity>
            <Dynamic>c:/devel/yard-ice/src/fpga/yard_ice.vhdl(365): </Dynamic>
            <Dynamic>&quot;UUUUUUUUUUUUUUUU&quot;</Dynamic>
            <Dynamic>s_ddr_cmd_dat</Dynamic>
            <Navigation>c:/devel/yard-ice/src/fpga/yard_ice.vhdl</Navigation>
            <Navigation>365</Navigation>
        </Message>
        <Message>
            <ID>35921303</ID>
            <Severity>Warning</Severity>
            <Dynamic>c:/devel/yard-ice/src/fpga/yard_ice.vhdl(367): </Dynamic>
            <Dynamic>'U'</Dynamic>
            <Dynamic>s_ddr_mwr_cyc</Dynamic>
            <Navigation>c:/devel/yard-ice/src/fpga/yard_ice.vhdl</Navigation>
            <Navigation>367</Navigation>
        </Message>
        <Message>
            <ID>35921303</ID>
            <Severity>Warning</Severity>
            <Dynamic>c:/devel/yard-ice/src/fpga/yard_ice.vhdl(368): </Dynamic>
            <Dynamic>'U'</Dynamic>
            <Dynamic>s_ddr_mwe_bst</Dynamic>
            <Navigation>c:/devel/yard-ice/src/fpga/yard_ice.vhdl</Navigation>
            <Navigation>368</Navigation>
        </Message>
        <Message>
            <ID>35921303</ID>
            <Severity>Warning</Severity>
            <Dynamic>c:/devel/yard-ice/src/fpga/yard_ice.vhdl(369): </Dynamic>
            <Dynamic>'U'</Dynamic>
            <Dynamic>s_ddr_mwr_stb</Dynamic>
            <Navigation>c:/devel/yard-ice/src/fpga/yard_ice.vhdl</Navigation>
            <Navigation>369</Navigation>
        </Message>
        <Message>
            <ID>35921303</ID>
            <Severity>Warning</Severity>
            <Dynamic>c:/devel/yard-ice/src/fpga/yard_ice.vhdl(372): </Dynamic>
            <Dynamic>&quot;UUUUUUUUUUUUUUUUUUUUU&quot;</Dynamic>
            <Dynamic>s_ddr_mwr_adr</Dynamic>
            <Navigation>c:/devel/yard-ice/src/fpga/yard_ice.vhdl</Navigation>
            <Navigation>372</Navigation>
        </Message>
        <Message>
            <ID>35921303</ID>
            <Severity>Warning</Severity>
            <Dynamic>c:/devel/yard-ice/src/fpga/yard_ice.vhdl(373): </Dynamic>
            <Dynamic>&quot;UUUUUUUUUUUUUUUUUUUUUUUUUUUUUUUU&quot;</Dynamic>
            <Dynamic>s_ddr_mwr_dat</Dynamic>
            <Navigation>c:/devel/yard-ice/src/fpga/yard_ice.vhdl</Navigation>
            <Navigation>373</Navigation>
        </Message>
        <Message>
            <ID>35921303</ID>
            <Severity>Warning</Severity>
            <Dynamic>c:/devel/yard-ice/src/fpga/yard_ice.vhdl(374): </Dynamic>
            <Dynamic>'U'</Dynamic>
            <Dynamic>s_ddr_mwr_bst</Dynamic>
            <Navigation>c:/devel/yard-ice/src/fpga/yard_ice.vhdl</Navigation>
            <Navigation>374</Navigation>
        </Message>
        <Message>
            <ID>35921303</ID>
            <Severity>Warning</Severity>
            <Dynamic>c:/devel/yard-ice/src/fpga/yard_ice.vhdl(376): </Dynamic>
            <Dynamic>'U'</Dynamic>
            <Dynamic>s_ddr_mrd_cyc</Dynamic>
            <Navigation>c:/devel/yard-ice/src/fpga/yard_ice.vhdl</Navigation>
            <Navigation>376</Navigation>
        </Message>
        <Message>
            <ID>35921303</ID>
            <Severity>Warning</Severity>
            <Dynamic>c:/devel/yard-ice/src/fpga/yard_ice.vhdl(377): </Dynamic>
            <Dynamic>'U'</Dynamic>
            <Dynamic>s_ddr_mrd_we</Dynamic>
            <Navigation>c:/devel/yard-ice/src/fpga/yard_ice.vhdl</Navigation>
            <Navigation>377</Navigation>
        </Message>
        <Message>
            <ID>35921303</ID>
            <Severity>Warning</Severity>
            <Dynamic>c:/devel/yard-ice/src/fpga/yard_ice.vhdl(378): </Dynamic>
            <Dynamic>'U'</Dynamic>
            <Dynamic>s_ddr_mrd_stb</Dynamic>
            <Navigation>c:/devel/yard-ice/src/fpga/yard_ice.vhdl</Navigation>
            <Navigation>378</Navigation>
        </Message>
        <Message>
            <ID>35921303</ID>
            <Severity>Warning</Severity>
            <Dynamic>c:/devel/yard-ice/src/fpga/yard_ice.vhdl(381): </Dynamic>
            <Dynamic>&quot;UUUUUUUUUUUUUUUUUUUUU&quot;</Dynamic>
            <Dynamic>s_ddr_mrd_adr</Dynamic>
            <Navigation>c:/devel/yard-ice/src/fpga/yard_ice.vhdl</Navigation>
            <Navigation>381</Navigation>
        </Message>
        <Message>
            <ID>35921303</ID>
            <Severity>Warning</Severity>
            <Dynamic>c:/devel/yard-ice/src/fpga/yard_ice.vhdl(383): </Dynamic>
            <Dynamic>'U'</Dynamic>
            <Dynamic>s_ddr_mrd_bst</Dynamic>
            <Navigation>c:/devel/yard-ice/src/fpga/yard_ice.vhdl</Navigation>
            <Navigation>383</Navigation>
        </Message>
        <Message>
            <ID>35921205</ID>
            <Severity>Warning</Severity>
            <Dynamic>c:/devel/yard-ice/src/fpga/yard_ice.vhdl(121): </Dynamic>
            <Dynamic>yard_ice</Dynamic>
            <Dynamic>structure</Dynamic>
            <Navigation>c:/devel/yard-ice/src/fpga/yard_ice.vhdl</Navigation>
            <Navigation>121</Navigation>
        </Message>
        <Message>
            <ID>35001537</ID>
            <Severity>Warning</Severity>
            <Dynamic>OB</Dynamic>
            <Dynamic>O</Dynamic>
        </Message>
        <Message>
            <ID>35001537</ID>
            <Severity>Warning</Severity>
            <Dynamic>OB</Dynamic>
            <Dynamic>O</Dynamic>
        </Message>
        <Message>
            <ID>35001537</ID>
            <Severity>Warning</Severity>
            <Dynamic>OB</Dynamic>
            <Dynamic>O</Dynamic>
        </Message>
        <Message>
            <ID>35001537</ID>
            <Severity>Warning</Severity>
            <Dynamic>OB</Dynamic>
            <Dynamic>O</Dynamic>
        </Message>
        <Message>
            <ID>35001537</ID>
            <Severity>Warning</Severity>
            <Dynamic>OB</Dynamic>
            <Dynamic>O</Dynamic>
        </Message>
        <Message>
            <ID>35001537</ID>
            <Severity>Warning</Severity>
            <Dynamic>OB</Dynamic>
            <Dynamic>O</Dynamic>
        </Message>
        <Message>
            <ID>35001537</ID>
            <Severity>Warning</Severity>
            <Dynamic>OB</Dynamic>
            <Dynamic>O</Dynamic>
        </Message>
        <Message>
            <ID>35001537</ID>
            <Severity>Warning</Severity>
            <Dynamic>OB</Dynamic>
            <Dynamic>O</Dynamic>
        </Message>
        <Message>
            <ID>35001537</ID>
            <Severity>Warning</Severity>
            <Dynamic>OB</Dynamic>
            <Dynamic>O</Dynamic>
        </Message>
        <Message>
            <ID>35001537</ID>
            <Severity>Warning</Severity>
            <Dynamic>OB</Dynamic>
            <Dynamic>O</Dynamic>
        </Message>
        <Message>
            <ID>35001537</ID>
            <Severity>Warning</Severity>
            <Dynamic>OB</Dynamic>
            <Dynamic>O</Dynamic>
        </Message>
        <Message>
            <ID>35001537</ID>
            <Severity>Warning</Severity>
            <Dynamic>OB</Dynamic>
            <Dynamic>O</Dynamic>
        </Message>
        <Message>
            <ID>35001537</ID>
            <Severity>Warning</Severity>
            <Dynamic>OB</Dynamic>
            <Dynamic>O</Dynamic>
        </Message>
        <Message>
            <ID>35001537</ID>
            <Severity>Warning</Severity>
            <Dynamic>OB</Dynamic>
            <Dynamic>O</Dynamic>
        </Message>
        <Message>
            <ID>35001537</ID>
            <Severity>Warning</Severity>
            <Dynamic>OB</Dynamic>
            <Dynamic>O</Dynamic>
        </Message>
        <Message>
            <ID>35001537</ID>
            <Severity>Warning</Severity>
            <Dynamic>OB</Dynamic>
            <Dynamic>O</Dynamic>
        </Message>
        <Message>
            <ID>35001537</ID>
            <Severity>Warning</Severity>
            <Dynamic>OB</Dynamic>
            <Dynamic>O</Dynamic>
        </Message>
        <Message>
            <ID>35001537</ID>
            <Severity>Warning</Severity>
            <Dynamic>OB</Dynamic>
            <Dynamic>O</Dynamic>
        </Message>
        <Message>
            <ID>35001537</ID>
            <Severity>Warning</Severity>
            <Dynamic>OB</Dynamic>
            <Dynamic>O</Dynamic>
        </Message>
        <Message>
            <ID>35001537</ID>
            <Severity>Warning</Severity>
            <Dynamic>OB</Dynamic>
            <Dynamic>O</Dynamic>
        </Message>
        <Message>
            <ID>35001537</ID>
            <Severity>Warning</Severity>
            <Dynamic>OB</Dynamic>
            <Dynamic>O</Dynamic>
        </Message>
        <Message>
            <ID>35002005</ID>
            <Severity>Warning</Severity>
            <Dynamic>ddr_ldqm</Dynamic>
        </Message>
        <Message>
            <ID>35002005</ID>
            <Severity>Warning</Severity>
            <Dynamic>ddr_udqm</Dynamic>
        </Message>
        <Message>
            <ID>35002005</ID>
            <Severity>Warning</Severity>
            <Dynamic>clk_aux</Dynamic>
        </Message>
        <Message>
            <ID>35001774</ID>
            <Severity>Info</Severity>
            <Dynamic>\cram_bus/s_cram_st</Dynamic>
            <Dynamic>one-hot</Dynamic>
        </Message>
        <Message>
            <ID>35001774</ID>
            <Severity>Info</Severity>
            <Dynamic>\shifter/rx/s_op_fifo.head</Dynamic>
            <Dynamic>one-hot</Dynamic>
        </Message>
        <Message>
            <ID>35001774</ID>
            <Severity>Info</Severity>
            <Dynamic>\cram_bus/reg_wr_fifo/s_sel_out</Dynamic>
            <Dynamic>one-hot</Dynamic>
        </Message>
        <Message>
            <ID>35001747</ID>
            <Severity>Warning</Severity>
            <Dynamic>11</Dynamic>
            <Dynamic>\mem_wr_addr/s_reg</Dynamic>
        </Message>
        <Message>
            <ID>35001747</ID>
            <Severity>Warning</Severity>
            <Dynamic>11</Dynamic>
            <Dynamic>\mem_rd_addr/s_reg</Dynamic>
        </Message>
        <Message>
            <ID>35001537</ID>
            <Severity>Warning</Severity>
            <Dynamic>OB</Dynamic>
            <Dynamic>O</Dynamic>
        </Message>
        <Message>
            <ID>35001537</ID>
            <Severity>Warning</Severity>
            <Dynamic>OB</Dynamic>
            <Dynamic>O</Dynamic>
        </Message>
        <Message>
            <ID>35001537</ID>
            <Severity>Warning</Severity>
            <Dynamic>OB</Dynamic>
            <Dynamic>O</Dynamic>
        </Message>
        <Message>
            <ID>35001537</ID>
            <Severity>Warning</Severity>
            <Dynamic>OB</Dynamic>
            <Dynamic>O</Dynamic>
        </Message>
        <Message>
            <ID>35001537</ID>
            <Severity>Warning</Severity>
            <Dynamic>OB</Dynamic>
            <Dynamic>O</Dynamic>
        </Message>
        <Message>
            <ID>35001537</ID>
            <Severity>Warning</Severity>
            <Dynamic>OB</Dynamic>
            <Dynamic>O</Dynamic>
        </Message>
        <Message>
            <ID>35001537</ID>
            <Severity>Warning</Severity>
            <Dynamic>OB</Dynamic>
            <Dynamic>O</Dynamic>
        </Message>
        <Message>
            <ID>35001537</ID>
            <Severity>Warning</Severity>
            <Dynamic>OB</Dynamic>
            <Dynamic>O</Dynamic>
        </Message>
        <Message>
            <ID>35001537</ID>
            <Severity>Warning</Severity>
            <Dynamic>OB</Dynamic>
            <Dynamic>O</Dynamic>
        </Message>
        <Message>
            <ID>35001537</ID>
            <Severity>Warning</Severity>
            <Dynamic>OB</Dynamic>
            <Dynamic>O</Dynamic>
        </Message>
        <Message>
            <ID>35001537</ID>
            <Severity>Warning</Severity>
            <Dynamic>OB</Dynamic>
            <Dynamic>O</Dynamic>
        </Message>
        <Message>
            <ID>35001537</ID>
            <Severity>Warning</Severity>
            <Dynamic>OB</Dynamic>
            <Dynamic>O</Dynamic>
        </Message>
        <Message>
            <ID>35001537</ID>
            <Severity>Warning</Severity>
            <Dynamic>OB</Dynamic>
            <Dynamic>O</Dynamic>
        </Message>
        <Message>
            <ID>35001537</ID>
            <Severity>Warning</Severity>
            <Dynamic>OB</Dynamic>
            <Dynamic>O</Dynamic>
        </Message>
        <Message>
            <ID>35001537</ID>
            <Severity>Warning</Severity>
            <Dynamic>OB</Dynamic>
            <Dynamic>O</Dynamic>
        </Message>
        <Message>
            <ID>35001537</ID>
            <Severity>Warning</Severity>
            <Dynamic>OB</Dynamic>
            <Dynamic>O</Dynamic>
        </Message>
        <Message>
            <ID>35001537</ID>
            <Severity>Warning</Severity>
            <Dynamic>OB</Dynamic>
            <Dynamic>O</Dynamic>
        </Message>
        <Message>
            <ID>35001537</ID>
            <Severity>Warning</Severity>
            <Dynamic>OB</Dynamic>
            <Dynamic>O</Dynamic>
        </Message>
        <Message>
            <ID>35001537</ID>
            <Severity>Warning</Severity>
            <Dynamic>OB</Dynamic>
            <Dynamic>O</Dynamic>
        </Message>
        <Message>
            <ID>35001537</ID>
            <Severity>Warning</Severity>
            <Dynamic>OB</Dynamic>
            <Dynamic>O</Dynamic>
        </Message>
        <Message>
            <ID>35001537</ID>
            <Severity>Warning</Severity>
            <Dynamic>OB</Dynamic>
            <Dynamic>O</Dynamic>
        </Message>
        <Message>
            <ID>35001537</ID>
            <Severity>Warning</Severity>
            <Dynamic>OB</Dynamic>
            <Dynamic>O</Dynamic>
        </Message>
        <Message>
            <ID>35002005</ID>
            <Severity>Warning</Severity>
            <Dynamic>clk_aux</Dynamic>
        </Message>
        <Message>
            <ID>35001263</ID>
            <Severity>Warning</Severity>
            <Dynamic>ddr_dq[15]</Dynamic>
        </Message>
        <Message>
            <ID>35001263</ID>
            <Severity>Warning</Severity>
            <Dynamic>ddr_dq[14]</Dynamic>
        </Message>
        <Message>
            <ID>35001263</ID>
            <Severity>Warning</Severity>
            <Dynamic>ddr_dq[13]</Dynamic>
        </Message>
        <Message>
            <ID>35001263</ID>
            <Severity>Warning</Severity>
            <Dynamic>ddr_dq[12]</Dynamic>
        </Message>
        <Message>
            <ID>35001263</ID>
            <Severity>Warning</Severity>
            <Dynamic>ddr_dq[11]</Dynamic>
        </Message>
        <Message>
            <ID>35001263</ID>
            <Severity>Warning</Severity>
            <Dynamic>ddr_dq[10]</Dynamic>
        </Message>
        <Message>
            <ID>35001263</ID>
            <Severity>Warning</Severity>
            <Dynamic>ddr_dq[9]</Dynamic>
        </Message>
        <Message>
            <ID>35001263</ID>
            <Severity>Warning</Severity>
            <Dynamic>ddr_dq[8]</Dynamic>
        </Message>
        <Message>
            <ID>35001263</ID>
            <Severity>Warning</Severity>
            <Dynamic>ddr_dq[7]</Dynamic>
        </Message>
        <Message>
            <ID>35001263</ID>
            <Severity>Warning</Severity>
            <Dynamic>ddr_dq[6]</Dynamic>
        </Message>
        <Message>
            <ID>35001263</ID>
            <Severity>Warning</Severity>
            <Dynamic>ddr_dq[5]</Dynamic>
        </Message>
        <Message>
            <ID>35001263</ID>
            <Severity>Warning</Severity>
            <Dynamic>ddr_dq[4]</Dynamic>
        </Message>
        <Message>
            <ID>35001263</ID>
            <Severity>Warning</Severity>
            <Dynamic>ddr_dq[3]</Dynamic>
        </Message>
        <Message>
            <ID>35001263</ID>
            <Severity>Warning</Severity>
            <Dynamic>ddr_dq[2]</Dynamic>
        </Message>
        <Message>
            <ID>35001263</ID>
            <Severity>Warning</Severity>
            <Dynamic>ddr_dq[1]</Dynamic>
        </Message>
        <Message>
            <ID>35001263</ID>
            <Severity>Warning</Severity>
            <Dynamic>ddr_dq[0]</Dynamic>
        </Message>
        <Message>
            <ID>35001263</ID>
            <Severity>Warning</Severity>
            <Dynamic>ddr_ldqs</Dynamic>
        </Message>
        <Message>
            <ID>35001263</ID>
            <Severity>Warning</Severity>
            <Dynamic>ddr_udqs</Dynamic>
        </Message>
        <Message>
            <ID>35001263</ID>
            <Severity>Warning</Severity>
            <Dynamic>ddr_addr[12]</Dynamic>
        </Message>
        <Message>
            <ID>35001263</ID>
            <Severity>Warning</Severity>
            <Dynamic>ddr_addr[11]</Dynamic>
        </Message>
        <Message>
            <ID>35001263</ID>
            <Severity>Warning</Severity>
            <Dynamic>ddr_addr[10]</Dynamic>
        </Message>
        <Message>
            <ID>35001263</ID>
            <Severity>Warning</Severity>
            <Dynamic>ddr_addr[9]</Dynamic>
        </Message>
        <Message>
            <ID>35001263</ID>
            <Severity>Warning</Severity>
            <Dynamic>ddr_addr[8]</Dynamic>
        </Message>
        <Message>
            <ID>35001263</ID>
            <Severity>Warning</Severity>
            <Dynamic>ddr_addr[7]</Dynamic>
        </Message>
        <Message>
            <ID>35001263</ID>
            <Severity>Warning</Severity>
            <Dynamic>ddr_addr[6]</Dynamic>
        </Message>
        <Message>
            <ID>35001263</ID>
            <Severity>Warning</Severity>
            <Dynamic>ddr_addr[5]</Dynamic>
        </Message>
        <Message>
            <ID>35001263</ID>
            <Severity>Warning</Severity>
            <Dynamic>ddr_addr[4]</Dynamic>
        </Message>
        <Message>
            <ID>35001263</ID>
            <Severity>Warning</Severity>
            <Dynamic>ddr_addr[3]</Dynamic>
        </Message>
        <Message>
            <ID>35001263</ID>
            <Severity>Warning</Severity>
            <Dynamic>ddr_addr[2]</Dynamic>
        </Message>
        <Message>
            <ID>35001263</ID>
            <Severity>Warning</Severity>
            <Dynamic>ddr_addr[1]</Dynamic>
        </Message>
        <Message>
            <ID>35001263</ID>
            <Severity>Warning</Severity>
            <Dynamic>ddr_addr[0]</Dynamic>
        </Message>
        <Message>
            <ID>35001263</ID>
            <Severity>Warning</Severity>
            <Dynamic>ddr_cke</Dynamic>
        </Message>
        <Message>
            <ID>35001263</ID>
            <Severity>Warning</Severity>
            <Dynamic>ddr_clk</Dynamic>
        </Message>
        <Message>
            <ID>35001263</ID>
            <Severity>Warning</Severity>
            <Dynamic>ddr_casn</Dynamic>
        </Message>
        <Message>
            <ID>35001263</ID>
            <Severity>Warning</Severity>
            <Dynamic>ddr_rasn</Dynamic>
        </Message>
        <Message>
            <ID>35001263</ID>
            <Severity>Warning</Severity>
            <Dynamic>ddr_wen</Dynamic>
        </Message>
        <Message>
            <ID>35001263</ID>
            <Severity>Warning</Severity>
            <Dynamic>ddr_csn0</Dynamic>
        </Message>
        <Message>
            <ID>35001263</ID>
            <Severity>Warning</Severity>
            <Dynamic>ddr_csn1</Dynamic>
        </Message>
        <Message>
            <ID>35001263</ID>
            <Severity>Warning</Severity>
            <Dynamic>ddr_ba[1]</Dynamic>
        </Message>
        <Message>
            <ID>35001263</ID>
            <Severity>Warning</Severity>
            <Dynamic>ddr_ba[0]</Dynamic>
        </Message>
        <Message>
            <ID>35001611</ID>
            <Severity>Warning</Severity>
        </Message>
        <Message>
            <ID>1166315</ID>
            <Severity>Error</Severity>
            <Dynamic>logical</Dynamic>
            <Dynamic>ddr_ctl</Dynamic>
            <Dynamic>ddr_sdram_dual</Dynamic>
        </Message>
    </Task>
    <Task name="MapTrace">
        <Message>
            <ID>70061003</ID>
            <Severity>Warning</Severity>
            <Dynamic>ddr_phy/Inst5_DQSDLLC</Dynamic>
        </Message>
    </Task>
    <Task name="PAR">
        <Message>
            <ID>66011008</ID>
            <Severity>Warning</Severity>
            <Dynamic>
   Signal=mclk_c_enable_95 loads=4 clock_loads=1</Dynamic>
        </Message>
        <Message>
            <ID>66011008</ID>
            <Severity>Warning</Severity>
            <Dynamic>
   Signal=mclk_c_enable_95 loads=4 clock_loads=1</Dynamic>
        </Message>
        <Message>
            <ID>70061003</ID>
            <Severity>Warning</Severity>
            <Dynamic>ddr_phy/Inst5_DQSDLLC</Dynamic>
        </Message>
    </Task>
</BaliMessageLog>